setup.py
aws_checker/__init__.py
aws_checker/aws_checker.py
aws_checker_basic.egg-info/PKG-INFO
aws_checker_basic.egg-info/SOURCES.txt
aws_checker_basic.egg-info/dependency_links.txt
aws_checker_basic.egg-info/top_level.txt