Metadata-Version: 1.1
Name: aws-checker-basic
Version: 0.1
Summary: List AWS resources
Home-page: https://github.com/diboanches/aws_checker
Author: diboan
Author-email: diboan@yandex.ru
License: UNKNOWN
Download-URL: https://github.com/diboanches/aws_checker
Platform: UNKNOWN
